{
  "name": "exgrizz-artifactory_pro",
  "version": "99.0.7",
  "author": "Bryan Belanger, patched by Eric Griswold",
  "summary": "Forked from autostructure/artifactory_pro",
  "license": "Apache-2.0",
  "source":  "https://github.com/e-gris/artifactory_pro.git",
  "project_page": "https://github.com/e-gris/artifactory_pro",
  "issues_url": "https://github.com/e-gris/artifactory_pro/issues",
  "dependencies": [
    {
      "name": "exgrizz-artifactory",
      "version_requirement": ">= 99.0.0"
    }
  ],
  "operatingsystem_support": [
    {
      "operatingsystem": "CentOS",
      "operatingsystemrelease": [
        "6",
        "7"
      ]
    },
    {
      "operatingsystem": "OracleLinux",
      "operatingsystemrelease": [
        "6",
        "7"
      ]
    },
    {
      "operatingsystem": "RedHat",
      "operatingsystemrelease": [
        "6",
        "7"
      ]
    }
  ]
}
